<?xml version = "1.0" encoding = "UTF-8"?>

<!DOCTYPE mapper PUBLIC "-//mybatis.org//DTD Mapper 3.0//EN" "http://mybatis.org/dtd/mybatis-3-mapper.dtd">

<mapper namespace = "com.solvd.library.dao.IUserDAO">
    <resultMap type = "com.solvd.library.bin.Users"
               id= "UserResultMap"   autoMapping="false">
        <result property = "id" column = "id"/>
        <result property = "name" column = "name"/>
        <result property = "email" column = "email"/>
        <result property = "address" column = "address"/>
        <result property = "age" column = "age"/>

    </resultMap>
        
    
    <select id = "getAll"  resultMap = "UserResultMap">
    
            SELECT * FROM USERS
    
    </select>
    
    <delete id= "delete" >
            
            DELETE from Users WHERE id = #{id}
     
    </delete>


        </mapper>